soccerbars/__init__.py
soccerbars/__main__.py
soccerbars/core.py
soccerbars-0.2.1.dist-info/LICENSE
soccerbars-0.2.1.dist-info/LICENSE.md
soccerbars-0.2.1.dist-info/METADATA
soccerbars-0.2.1.dist-info/WHEEL
soccerbars-0.2.1.dist-info/entry_points.txt
soccerbars-0.2.1.dist-info/RECORD
