Metadata-Version: 2.1
Name: soccerbars
Version: 0.2.1
Summary: Word-sized tallies of association football results using multivariate sparklines based on Gestalt theory (gestaltlines).
Home-page: https://github.com/meakbiyik/soccerbars
License: MIT
Keywords: soccer,sparklines,football,association-football
Author: M. Eren Akbiyik
Author-email: erenakbiyik@gmail.com
Requires-Python: >=3.8,<4.0
Classifier: License :: OSI Approved :: MIT License
Classifier: Programming Language :: Python :: 3
Classifier: Programming Language :: Python :: 3.8
Classifier: Programming Language :: Python :: 3.9
Classifier: Programming Language :: Python :: 3.10
Classifier: Programming Language :: Python :: 3.11
Provides-Extra: cli
Requires-Dist: click (>=7.1.2,<8.0.0) ; extra == "cli"
Requires-Dist: click-help-colors (>=0.9,<0.10) ; extra == "cli"
Requires-Dist: colorama (>=0.4.4,<0.5.0) ; extra == "cli"
Requires-Dist: matplotlib (>=3.7.1,<4.0.0)
Requires-Dist: numpy (>=1.24.0,<2.0.0)
Requires-Dist: pandas (>=2.0.3,<3.0.0) ; extra == "cli"
Project-URL: Repository, https://github.com/meakbiyik/soccerbars
